Metadata-Version: 1.0
Name: dada-cli
Version: 0.0.9
Summary: The fully-featured cli for dada-lake
Home-page: http://globally.ltd
Author: gltd
Author-email: hey@gltd.email
License: UNKNOWN
Platform: UNKNOWN
